VERSION
quantregpy-0.1.56.dist-info/LICENSE
quantregpy-0.1.56.dist-info/WHEEL
quantregpy-0.1.56.dist-info/top_level.txt
quantregpy-0.1.56.dist-info/RECORD
quantregpy-0.1.56.dist-info/METADATA
quantregpy/quantreg.py
quantregpy/setup.py
quantregpy/__init__.py
quantregpy/_fortran.cpython-39-x86_64-linux-gnu.so
quantregpy/_fortran/blas_src/dgemv.f
quantregpy/_fortran/blas_src/dsyr.f
quantregpy/_fortran/blas_src/dpotrf.f
quantregpy/_fortran/blas_src/dcopy.f
quantregpy/_fortran/blas_src/dgemm.f
quantregpy/_fortran/blas_src/dlaisnan.f
quantregpy/_fortran/blas_src/dpotrs.f
quantregpy/_fortran/blas_src/ieeeck.f
quantregpy/_fortran/blas_src/dtrsm.f
quantregpy/_fortran/blas_src/disnan.f
quantregpy/_fortran/blas_src/dsyrk.f
quantregpy/_fortran/blas_src/dposv.f
quantregpy/_fortran/blas_src/xerbla.f
quantregpy/_fortran/blas_src/iparmq.f
quantregpy/_fortran/blas_src/dpotrf2.f
quantregpy/_fortran/blas_src/lsame.f
quantregpy/_fortran/blas_src/ilaenv.f
quantregpy.libs/libgfortran-040039e1.so.5.0.0
quantregpy.libs/libquadmath-96973f99.so.0.0.0
