Metadata-Version: 2.1
Name: quantregpy
Version: 0.1.56
Summary: Translation of R quantreg for python
Home-page: https://github.com/quantregpy
Maintainer: David Kaftan and Paul Kaefer
Maintainer-email: kaftand@gmail.com
License: GNU
Requires-Python: >=3.6
License-File: LICENSE
Requires-Dist: patsy
Requires-Dist: numpy
Requires-Dist: scipy
Requires-Dist: pandas
Requires-Dist: scikit-learn
